{
  "mrr": 0.16666666666666666,
  "ndcg": 0.157873529284268,
  "model": "intfloat/e5-mistral-7b-instruct",
  "dataset": "fiqa",
  "query_id": "2296",
  "k": 10,
  "use_reranker": false,
  "initial_k": 10,
  "ranking": [
    "532515",
    "58353",
    "430689",
    "91201",
    "135509",
    "106424",
    "94230",
    "83330",
    "336847",
    "333140"
  ],
  "relevant_docs": [
    "119298",
    "400009",
    "396853",
    "366594",
    "83330",
    "130850",
    "106424",
    "279897",
    "253563"
  ]
}