{
  "mrr": 1.0,
  "ndcg": 1.0,
  "model": "intfloat/e5-mistral-7b-instruct",
  "dataset": "fever",
  "query_id": "64966",
  "k": 10,
  "use_reranker": true,
  "initial_k": 100,
  "ranking": [
    "Camp_Flog_Gnaw",
    "Horror_convention",
    "Camp_(style)",
    "Warped_Tour",
    "Rock_festival",
    "Rock_'n_Roll_Fantasy_Camp",
    "MTV_Europe_Music_Awards",
    "Journalism",
    "History_of_music",
    "2009_Scream_Awards"
  ],
  "relevant_docs": [
    "Camp_Flog_Gnaw"
  ],
  "tokens_reranked": 16111
}