{
  "mrr": 1.0,
  "ndcg": 0.7653606369886217,
  "model": "nomic-ai/nomic-embed-text-v1.5",
  "dataset": "fever",
  "query_id": "179815",
  "k": 10,
  "use_reranker": true,
  "initial_k": 100,
  "ranking": [
    "Vic_Mensa",
    "Innanetape",
    "Show_Me_Love_(album)",
    "Dessa",
    "Mensa_International",
    "Love_Has_Left_the_Room",
    "Vic_Tanny",
    "MTV_Video_Music_Award",
    "Roaring_Twenties",
    "1993_NBA_Playoffs"
  ],
  "relevant_docs": [
    "Vic_Mensa",
    "Innanetape",
    "Chance_the_Rapper"
  ],
  "tokens_reranked": 33852
}