{
  "mrr": 0.16666666666666666,
  "ndcg": 0.07839826897867533,
  "model": "voyageai/voyage-3-lite",
  "dataset": "dbpedia",
  "query_id": "SemSearch_ES-20",
  "k": 10,
  "use_reranker": true,
  "initial_k": 100,
  "ranking": [
    "<dbpedia:Carolina,_Puerto_Rico>",
    "<dbpedia:Carolina,_Alabama>",
    "<dbpedia:Carolina,_U.S._Virgin_Islands>",
    "<dbpedia:Carolina,_Alamance_County,_North_Carolina>",
    "<dbpedia:Carolina,_Santa_Maria>",
    "<dbpedia:Province_of_Carolina>",
    "<dbpedia:Carolina_(film)>",
    "<dbpedia:Carolina_(state_song)>",
    "<dbpedia:Halesia_carolina>",
    "<dbpedia:Carolina_(Eric_Church_album)>"
  ],
  "relevant_docs": [
    "<dbpedia:North_Carolina_Highway_49>",
    "<dbpedia:List_of_newspapers_in_North_Carolina>",
    "<dbpedia:North_Carolina_Highway_201>",
    "<dbpedia:Sullivan's_Island,_South_Carolina>",
    "<dbpedia:Western_North_Carolina>",
    "<dbpedia:Index_of_North_Carolina-related_articles>",
    "<dbpedia:South_Carolina_Department_of_Transportation>",
    "<dbpedia:Province_of_South_Carolina>",
    "<dbpedia:North_Carolina>",
    "<dbpedia:North_Carolina_Senate>",
    "<dbpedia:List_of_counties_in_South_Carolina>",
    "<dbpedia:Meggett,_South_Carolina>",
    "<dbpedia:South_Carolina_Highway_9>",
    "<dbpedia:U.S._Route_701>",
    "<dbpedia:South_Carolina>",
    "<dbpedia:List_of_municipalities_in_North_Carolina>",
    "<dbpedia:List_of_townships_in_North_Carolina>",
    "<dbpedia:North_Carolina_House_of_Representatives>",
    "<dbpedia:North_Carolina_Agricultural_and_Technical_State_University>",
    "<dbpedia:University_of_South_Carolina>",
    "<dbpedia:List_of_museums_in_North_Carolina>",
    "<dbpedia:Raleigh,_North_Carolina>",
    "<dbpedia:List_of_counties_in_North_Carolina>",
    "<dbpedia:Wake_County,_North_Carolina>",
    "<dbpedia:Index_of_South_Carolina-related_articles>",
    "<dbpedia:Province_of_Carolina>"
  ],
  "tokens_reranked": 2591
}