{
  "mrr": 1.0,
  "ndcg": 0.46927872602275644,
  "model": "voyageai/voyage-3",
  "dataset": "climate-fever",
  "query_id": "1774",
  "k": 10,
  "use_reranker": false,
  "initial_k": 10,
  "ranking": [
    "CLOUD_experiment",
    "Cloud_formation_and_climate_change",
    "TopHat_(telescope)",
    "Climate_engineering",
    "Clouds_and_the_Earth's_Radiant_Energy_System",
    "Iris_hypothesis",
    "List_of_scientists_opposing_the_mainstream_scientific_assessment_of_global_warming",
    "Scientific_consensus_on_climate_change",
    "Cosmic_ray",
    "Milankovitch_cycles"
  ],
  "relevant_docs": [
    "Attribution_of_recent_climate_change",
    "Climate_change_(general_concept)",
    "CLOUD_experiment"
  ]
}